{"components_avatar.md":"b7ce9207","components_tag.md":"01d1780b","index.md":"99d30450","components_svg-icon.md":"24fd4ce2","components_avatar-group.md":"dba1ebc6","components_back-top.md":"bd8d247b","components_breadcrumb.md":"b579e93b","components_box.md":"840c64d7","components_calendar.md":"ba4478ba","components_card.md":"7898bcce","components_checkbox.md":"3d4a7a1c","components_close-btn.md":"491f0d99","components_color.md":"6af1e399","components_confirm-box.md":"fdb4a8bb","components_count-down.md":"c49a5625","components_collapse-animation.md":"64eac4ef","components_date-picker.md":"cc061ed0","components_button.md":"29776f1c","components_divider.md":"7965adcd","components_drawer.md":"f0cc9b3b","components_dropdown.md":"b55c1bd2","components_dialog.md":"e8fe9df7","components_expand-card.md":"c472efc5","components_fighting-global.md":"e7bc3b9e","components_image-preview.md":"5eb1a05d","components_form.md":"1319eb27","components_infinite-scrolling.md":"8991b2d5","components_image.md":"c4de496e","components_interface.md":"f892d3ba","components_empty.md":"1d7b5427","components_input-number.md":"0ef063ba","components_list.md":"ba324449","components_input.md":"f19edd5c","components_select.md":"deeb9aff","components_skeleton.md":"5a0023c9","components_space.md":"02e5efea","components_loading.md":"e55bae75","components_sticky-card.md":"f10912c4","components_swap.md":"4197be37","components_time-picker.md":"a9e44e8c","components_notification.md":"1655b834","components_switch.md":"a2ed27f6","components_layout.md":"89f207d0","components_link.md":"dd47aa4e","components_toolbar.md":"6937e186","components_page-header.md":"b8213e93","docs_join.md":"e1b5c3c7","docs_introduce.md":"86da1891","docs_milepost.md":"ba030c23","theme_start.md":"64036df9","components_message.md":"21beae88","components_pagination.md":"ce00a4fe","components_rate.md":"a8f757a4","components_progress.md":"164b8544","components_radio.md":"2b083cbb","components_ripple.md":"6bfba0e7","docs_install.md":"39d4d377","components_watermark.md":"f7264a75","docs_import.md":"f6aa0738","components_tabs.md":"6e559647","components_trigger.md":"2fbeb88b","components_slider.md":"e559bd18","components_menu.md":"37dd7cde","components_tree.md":"eb4e7fd9","docs_changelog.md":"49071cc2","components_textarea.md":"08c86bef","components_up-load.md":"2553be32","components_table.md":"940bdf73","components_tooltip.md":"508eeae4","docs_contributing.md":"cd3a4b21","components_text.md":"2efdc8cb","readme.md":"e5e9b2a6","components_alert.md":"c4e6cbee","components_number-animate.md":"0b12cf3d","components_badge.md":"fbe7d2fa"}
