{"components_loading.md":"56b23b5f","components_number-animate.md":"91a2bffa","components_page-header.md":"076dab27","components_date-picker.md":"1f8230da","components_close-btn.md":"4a78d826","components_collapse-animation.md":"b9b9cd71","components_color.md":"c1a4ab6a","components_confirm-box.md":"f70ba11a","components_count-down.md":"887759ea","components_swap.md":"a1c4e3bd","components_list.md":"caf12a4e","components_interface.md":"0743a6cd","components_menu.md":"be47f81a","components_layout.md":"7e37c9fe","components_watermark.md":"f3868666","docs_contributing.md":"d5ef1c6d","docs_import.md":"6f645b5e","docs_install.md":"685dabcb","docs_introduce.md":"11037507","docs_join.md":"35483430","docs_milepost.md":"b508ef28","index.md":"d84df52a","theme_start.md":"9caf01e6","components_pagination.md":"e67b8619","components_avatar.md":"15e22b13","components_message.md":"2e2f1bd8","components_input.md":"805c312f","components_drawer.md":"f64ad5a7","components_dropdown.md":"7ce90276","components_fighting-global.md":"6b57a634","components_card.md":"5a0afd84","components_checkbox.md":"94372236","components_form.md":"c4980033","components_image-preview.md":"d5fd34d9","components_progress.md":"12df8748","components_input-number.md":"ecba1204","components_radio.md":"8feb2532","components_rate.md":"f2ccf569","components_slider.md":"b028ef54","components_switch.md":"009cc55f","components_toolbar.md":"4c86ae18","components_tooltip.md":"389ad971","components_trigger.md":"faa640c8","components_up-load.md":"bce3cef2","components_avatar-group.md":"5e77be05","components_notification.md":"e7d1b39d","components_ripple.md":"908fed6c","components_select.md":"daaac489","components_empty.md":"cf840e42","components_skeleton.md":"65d09735","components_breadcrumb.md":"0c08c1b8","components_alert.md":"c0b477fc","components_space.md":"878f1cda","components_time-picker.md":"9dc032b1","components_image.md":"831eedb1","components_infinite-scrolling.md":"0ea92536","components_tag.md":"60323019","readme.md":"0bfacc29","components_text.md":"bfe3d771","components_dialog.md":"31dec548","docs_changelog.md":"7827ebcb","components_back-top.md":"48843e41","components_box.md":"a4f9ff33","components_badge.md":"002f68f9","components_calendar.md":"140420dd","components_link.md":"90a42096","components_divider.md":"a21c3624","components_expand-card.md":"41b575cc","components_table.md":"de822dc5","components_button.md":"b15f22bc","components_sticky-card.md":"0bb1be21","components_tabs.md":"2fbbca3e","components_tree.md":"372da7a5","components_textarea.md":"0b0ff66e","components_svg-icon.md":"7e5bf7a2"}
